uv_stats/__init__.py
uv_stats/__main__.py
uv_stats/cli.py
uv_stats/manager.py
uv_stats/monitoring.py
uv_stats/requests.py
uv_stats/sources.py
uv_stats-0.1.1.dist-info/METADATA
uv_stats-0.1.1.dist-info/WHEEL
uv_stats-0.1.1.dist-info/entry_points.txt
uv_stats-0.1.1.dist-info/top_level.txt
uv_stats-0.1.1.dist-info/RECORD
