Metadata-Version: 2.1
Name: uv-stats
Version: 0.1.1
Summary: Make pritty statistic about package in concole
Author-email: Alekse Marusich <alekse.marusich@rocshers.com>
License: MIT
Keywords: rocshers,uvxt,uv,pypi,clickhouse
Classifier: License :: OSI Approved :: MIT License
Classifier: Intended Audience :: Developers
Classifier: Intended Audience :: Information Technology
Classifier: Intended Audience :: System Administrators
Classifier: Operating System :: OS Independent
Classifier: Topic :: Software Development :: Build Tools
Classifier: Topic :: Software Development :: Libraries :: Python Modules
Classifier: Topic :: Software Development :: Libraries
Classifier: Topic :: Software Development
Classifier: Topic :: System :: Archiving :: Packaging
Classifier: Topic :: System :: Installation/Setup
Classifier: Topic :: System :: Software Distribution
Classifier: Programming Language :: Python :: 3 :: Only
Classifier: Programming Language :: Python :: 3.12
Classifier: Programming Language :: Python :: 3.11
Classifier: Programming Language :: Python :: 3.10
Classifier: Programming Language :: Python :: 3.9
Classifier: Programming Language :: Python :: 3
Classifier: Programming Language :: Python
Requires-Python: >=3.9
Requires-Dist: rich>=13.9.3
Requires-Dist: package-schemes==0.1.2
Requires-Dist: clickhouse-connect>=0.8.5
Requires-Dist: typer>=0.12.5
Requires-Dist: pydantic>=2.9.2
